pyonemap/__init__.py
pyonemap/converter.py
pyonemap/core.py
pyonemap/onemap.py
pyonemap/planning_area.py
pyonemap/population_query.py
pyonemap/reverse_geocode.py
pyonemap/routing.py
pyonemap/themes.py
pyonemap/utils.py
pyonemap-0.10.0.dist-info/LICENSE
pyonemap-0.10.0.dist-info/METADATA
pyonemap-0.10.0.dist-info/WHEEL
pyonemap-0.10.0.dist-info/top_level.txt
pyonemap-0.10.0.dist-info/RECORD
