Metadata-Version: 2.1
Name: pyonemap
Version: 0.10.0
Summary: A Python package for interacting with OneMap API
Home-page: https://github.com/chengguan/pyonemap
Author: Teo Cheng Guan
Author-email: chengguan.teo@gmail.com
License: UNKNOWN
Platform: UNKNOWN
Classifier: Development Status :: 3 - Alpha
Classifier: Intended Audience :: Developers
Classifier: License :: OSI Approved :: MIT License
Classifier: Programming Language :: Python :: 3
Classifier: Programming Language :: Python :: 3.6
Classifier: Programming Language :: Python :: 3.7
Classifier: Programming Language :: Python :: 3.8
Classifier: Programming Language :: Python :: 3.9
